[
  {
    "email": "peter.wang@adbridgehq.com ",
    "status": "active",
    "name": "Peter Wang",
    "phone": "15888888888",
    "weixin": "15888888888",
    "qq": "8889999",
    "skype": "peter"
  },
  {
    "email": "mike.cao@adbridgehq.com ",
    "status": "active",
    "name": "Mike Cao",
    "phone": "15888888888",
    "weixin": "15888888888",
    "qq": "8889999",
    "skype": "mike"
  },
  {
    "email": "peter.wang@adbridgehq.com ",
    "status": "active",
    "name": "Peter Wang",
    "phone": "15888888888",
    "weixin": "15888888888",
    "qq": "8889999",
    "skype": "peter"
  },
  {
    "email": "mike.cao@adbridgehq.com ",
    "status": "active",
    "name": "Mike Cao",
    "phone": "15888888888",
    "weixin": "15888888888",
    "qq": "8889999",
    "skype": "mike"
  },
  {
    "email": "peter.wang@adbridgehq.com ",
    "status": "active",
    "name": "Peter Wang",
    "phone": "15888888888",
    "weixin": "15888888888",
    "qq": "8889999",
    "skype": "peter"
  },
  {
    "email": "mike.cao@adbridgehq.com ",
    "status": "active",
    "name": "Mike Cao",
    "phone": "15888888888",
    "weixin": "15888888888",
    "qq": "8889999",
    "skype": "mike"
  },
  {
    "email": "peter.wang@adbridgehq.com ",
    "status": "active",
    "name": "Peter Wang",
    "phone": "15888888888",
    "weixin": "15888888888",
    "qq": "8889999",
    "skype": "peter"
  },
  {
    "email": "mike.cao@adbridgehq.com ",
    "status": "active",
    "name": "Mike Cao",
    "phone": "15888888888",
    "weixin": "15888888888",
    "qq": "8889999",
    "skype": "mike"
  }
]